{"template_file":"main.css.tt","path":"/usr/local/cpanel/3rdparty/share/site_templates","thingsIDo":"Promote the use of recycle wood in commercial and private sector in Hong Kong","template":"about_me","includes":{},"instagramLink":"https://www.instagram.com/iwra_2024/","docroot":"/home/iwra/public_html","linkedinLink":"","accomplishments":"Support from major management company and green building associations","twitterLink":"","aboutMeHeading":"A Non-profit organization","aboutMe":"Established 2024","tagLine":"www.iwra.hk","fullName":"Innovative Wood Recycle Association Limited","githubLink":"","google_analytics_key":"","domain_url":"//iwra.hk","aboutMeTagLine":"www.iwra.hk","avatarURL":"","sectionHeaderColor":"#bb8a21","sectionSeparatorColor":"#41c13e","emailAddress":"info@iwra.hk","facebookLink":"https://www.facebook.com/share/g/1RCYgsT4PMquAp1G/","siteMajorColor":"#ca9449"}